[
    {
        "id": "3738",
        "player_name": "Serhou Guirassy",
        "games": "24",
        "time": "1817",
        "goals": "12",
        "xG": "13.461812105029821",
        "assists": "1",
        "xA": "1.762090252712369",
        "shots": "60",
        "key_passes": "17",
        "yellow_cards": "2",
        "red_cards": "0",
        "position": "F S",
        "team_title": "Borussia Dortmund",
        "npg": "11",
        "npxG": "11.188482072204351",
        "xGChain": "12.726464562118053",
        "xGBuildup": "2.736947411671281"
    },
    {
        "id": "8137",
        "player_name": "Maximilian Beier",
        "games": "23",
        "time": "1387",
        "goals": "8",
        "xG": "6.404220134019852",
        "assists": "4",
        "xA": "2.799117830581963",
        "shots": "36",
        "key_passes": "17",
        "yellow_cards": "2",
        "red_cards": "0",
        "position": "D F M S",
        "team_title": "Borussia Dortmund",
        "npg": "8",
        "npxG": "6.404220134019852",
        "xGChain": "11.104442337527871",
        "xGBuildup": "2.680294318124652"
    },
    {
        "id": "261",
        "player_name": "Julian Brandt",
        "games": "20",
        "time": "1210",
        "goals": "6",
        "xG": "4.301542589440942",
        "assists": "3",
        "xA": "3.3471111487597227",
        "shots": "26",
        "key_passes": "23",
        "yellow_cards": "0",
        "red_cards": "0",
        "position": "F M S",
        "team_title": "Borussia Dortmund",
        "npg": "6",
        "npxG": "4.301542589440942",
        "xGChain": "9.758924817666411",
        "xGBuildup": "3.7042540684342384"
    },
    {
        "id": "10772",
        "player_name": "Karim Adeyemi",
        "games": "23",
        "time": "1035",
        "goals": "5",
        "xG": "3.587473511695862",
        "assists": "3",
        "xA": "2.805378654971719",
        "shots": "24",
        "key_passes": "13",
        "yellow_cards": "3",
        "red_cards": "0",
        "position": "F M S",
        "team_title": "Borussia Dortmund",
        "npg": "5",
        "npxG": "3.587473511695862",
        "xGChain": "9.705049104988575",
        "xGBuildup": "4.054235387593508"
    },
    {
        "id": "7485",
        "player_name": "Nico Schlotterbeck",
        "games": "19",
        "time": "1710",
        "goals": "4",
        "xG": "3.0541223054751754",
        "assists": "1",
        "xA": "0.8246109932661057",
        "shots": "27",
        "key_passes": "7",
        "yellow_cards": "6",
        "red_cards": "0",
        "position": "D",
        "team_title": "Borussia Dortmund",
        "npg": "4",
        "npxG": "3.0541223054751754",
        "xGChain": "7.4791507218033075",
        "xGBuildup": "6.600985297933221"
    },
    {
        "id": "604",
        "player_name": "Emre Can",
        "games": "9",
        "time": "627",
        "goals": "3",
        "xG": "2.363978619687259",
        "assists": "0",
        "xA": "0",
        "shots": "5",
        "key_passes": "0",
        "yellow_cards": "3",
        "red_cards": "0",
        "position": "D S",
        "team_title": "Borussia Dortmund",
        "npg": "0",
        "npxG": "0.09064858686178923",
        "xGChain": "2.4536785297095776",
        "xGBuildup": "2.376001711934805"
    },
    {
        "id": "106",
        "player_name": "Waldemar Anton",
        "games": "23",
        "time": "2070",
        "goals": "2",
        "xG": "1.2234948333352804",
        "assists": "0",
        "xA": "0.20181455928832293",
        "shots": "12",
        "key_passes": "6",
        "yellow_cards": "3",
        "red_cards": "0",
        "position": "D",
        "team_title": "Borussia Dortmund",
        "npg": "2",
        "npxG": "1.2234948333352804",
        "xGChain": "8.035093756392598",
        "xGBuildup": "7.801926815882325"
    },
    {
        "id": "3349",
        "player_name": "Ramy Bensebaini",
        "games": "16",
        "time": "1164",
        "goals": "2",
        "xG": "1.0735344933345914",
        "assists": "0",
        "xA": "0.23229102790355682",
        "shots": "10",
        "key_passes": "6",
        "yellow_cards": "5",
        "red_cards": "0",
        "position": "D S",
        "team_title": "Borussia Dortmund",
        "npg": "2",
        "npxG": "1.0735344933345914",
        "xGChain": "5.70726253837347",
        "xGBuildup": "5.521258655935526"
    },
    {
        "id": "9202",
        "player_name": "Felix Nmecha",
        "games": "25",
        "time": "1928",
        "goals": "2",
        "xG": "1.951179763302207",
        "assists": "3",
        "xA": "1.8036808986216784",
        "shots": "27",
        "key_passes": "19",
        "yellow_cards": "0",
        "red_cards": "0",
        "position": "M S",
        "team_title": "Borussia Dortmund",
        "npg": "2",
        "npxG": "1.951179763302207",
        "xGChain": "10.043179295957088",
        "xGBuildup": "7.769462179392576"
    },
    {
        "id": "9356",
        "player_name": "Carney Chukwuemeka",
        "games": "20",
        "time": "626",
        "goals": "2",
        "xG": "2.304413612931967",
        "assists": "0",
        "xA": "0.5800747573375702",
        "shots": "14",
        "key_passes": "10",
        "yellow_cards": "1",
        "red_cards": "0",
        "position": "F M S",
        "team_title": "Borussia Dortmund",
        "npg": "2",
        "npxG": "2.304413612931967",
        "xGChain": "4.551490565761924",
        "xGBuildup": "2.151603424921632"
    },
    {
        "id": "13424",
        "player_name": "Daniel Svensson",
        "games": "25",
        "time": "1958",
        "goals": "2",
        "xG": "1.877221655100584",
        "assists": "2",
        "xA": "3.175162060186267",
        "shots": "9",
        "key_passes": "29",
        "yellow_cards": "0",
        "red_cards": "0",
        "position": "D M S",
        "team_title": "Borussia Dortmund",
        "npg": "2",
        "npxG": "1.877221655100584",
        "xGChain": "9.186520086601377",
        "xGBuildup": "6.000463562086225"
    },
    {
        "id": "5248",
        "player_name": "Marcel Sabitzer",
        "games": "18",
        "time": "1194",
        "goals": "1",
        "xG": "1.0127577241510153",
        "assists": "2",
        "xA": "1.698750525712967",
        "shots": "17",
        "key_passes": "9",
        "yellow_cards": "2",
        "red_cards": "0",
        "position": "M S",
        "team_title": "Borussia Dortmund",
        "npg": "1",
        "npxG": "1.0127577241510153",
        "xGChain": "4.636145263910294",
        "xGBuildup": "2.5048743300139904"
    },
    {
        "id": "8778",
        "player_name": "Fabio Silva",
        "games": "19",
        "time": "552",
        "goals": "1",
        "xG": "1.3864562008529902",
        "assists": "5",
        "xA": "2.1485821530222893",
        "shots": "16",
        "key_passes": "15",
        "yellow_cards": "3",
        "red_cards": "0",
        "position": "F M S",
        "team_title": "Borussia Dortmund",
        "npg": "1",
        "npxG": "1.3864562008529902",
        "xGChain": "4.122356036677957",
        "xGBuildup": "1.2083331122994423"
    },
    {
        "id": "10946",
        "player_name": "Yan Couto",
        "games": "16",
        "time": "979",
        "goals": "1",
        "xG": "0.5621986016631126",
        "assists": "2",
        "xA": "2.849770877510309",
        "shots": "8",
        "key_passes": "17",
        "yellow_cards": "4",
        "red_cards": "0",
        "position": "D M S",
        "team_title": "Borussia Dortmund",
        "npg": "1",
        "npxG": "0.5621986016631126",
        "xGChain": "6.485835496336222",
        "xGBuildup": "4.392777647823095"
    },
    {
        "id": "13460",
        "player_name": "Aaron Anselmino",
        "games": "6",
        "time": "368",
        "goals": "1",
        "xG": "0.05440906062722206",
        "assists": "0",
        "xA": "0",
        "shots": "1",
        "key_passes": "0",
        "yellow_cards": "0",
        "red_cards": "0",
        "position": "D S",
        "team_title": "Borussia Dortmund",
        "npg": "1",
        "npxG": "0.05440906062722206",
        "xGChain": "1.099787350744009",
        "xGBuildup": "1.099787350744009"
    },
    {
        "id": "75",
        "player_name": "Niklas Süle",
        "games": "9",
        "time": "445",
        "goals": "0",
        "xG": "0.03355417028069496",
        "assists": "1",
        "xA": "0.2960160970687866",
        "shots": "2",
        "key_passes": "2",
        "yellow_cards": "3",
        "red_cards": "0",
        "position": "D S",
        "team_title": "Borussia Dortmund",
        "npg": "0",
        "npxG": "0.03355417028069496",
        "xGChain": "2.3257176280021667",
        "xGBuildup": "2.232322722673416"
    },
    {
        "id": "239",
        "player_name": "Pascal Groß",
        "games": "11",
        "time": "619",
        "goals": "0",
        "xG": "0.8347828388214111",
        "assists": "1",
        "xA": "1.3404343351721764",
        "shots": "8",
        "key_passes": "11",
        "yellow_cards": "0",
        "red_cards": "0",
        "position": "M S",
        "team_title": "Borussia Dortmund",
        "npg": "0",
        "npxG": "0.8347828388214111",
        "xGChain": "4.495197154581547",
        "xGBuildup": "3.2702609561383724"
    },
    {
        "id": "5288",
        "player_name": "Gregor Kobel",
        "games": "25",
        "time": "2250",
        "goals": "0",
        "xG": "0",
        "assists": "0",
        "xA": "0",
        "shots": "0",
        "key_passes": "0",
        "yellow_cards": "2",
        "red_cards": "0",
        "position": "GK",
        "team_title": "Borussia Dortmund",
        "npg": "0",
        "npxG": "0",
        "xGChain": "4.282162766903639",
        "xGBuildup": "4.282162766903639"
    },
    {
        "id": "5294",
        "player_name": "Salih Özcan",
        "games": "7",
        "time": "19",
        "goals": "0",
        "xG": "0.1352226883172989",
        "assists": "0",
        "xA": "0",
        "shots": "1",
        "key_passes": "0",
        "yellow_cards": "0",
        "red_cards": "0",
        "position": "S",
        "team_title": "Borussia Dortmund",
        "npg": "0",
        "npxG": "0.1352226883172989",
        "xGChain": "0.6293506138026714",
        "xGBuildup": "0.49412792548537254"
    },
    {
        "id": "7997",
        "player_name": "Julian Ryerson",
        "games": "22",
        "time": "1499",
        "goals": "0",
        "xG": "0.5392383337020874",
        "assists": "11",
        "xA": "6.469990607351065",
        "shots": "8",
        "key_passes": "35",
        "yellow_cards": "5",
        "red_cards": "0",
        "position": "D S",
        "team_title": "Borussia Dortmund",
        "npg": "0",
        "npxG": "0.5392383337020874",
        "xGChain": "8.784688783809543",
        "xGBuildup": "6.604233404621482"
    },
    {
        "id": "13017",
        "player_name": "Filippo Mané",
        "games": "4",
        "time": "142",
        "goals": "0",
        "xG": "0",
        "assists": "0",
        "xA": "0",
        "shots": "0",
        "key_passes": "0",
        "yellow_cards": "0",
        "red_cards": "1",
        "position": "D S",
        "team_title": "Borussia Dortmund",
        "npg": "0",
        "npxG": "0",
        "xGChain": "0.6807209551334381",
        "xGBuildup": "0.6807209551334381"
    },
    {
        "id": "13887",
        "player_name": "Jobe Bellingham",
        "games": "23",
        "time": "1015",
        "goals": "0",
        "xG": "0.627767626196146",
        "assists": "1",
        "xA": "0.43259834684431553",
        "shots": "11",
        "key_passes": "4",
        "yellow_cards": "1",
        "red_cards": "1",
        "position": "M S",
        "team_title": "Borussia Dortmund",
        "npg": "0",
        "npxG": "0.627767626196146",
        "xGChain": "5.121664065867662",
        "xGBuildup": "4.420797988772392"
    },
    {
        "id": "14420",
        "player_name": "Luca Reggiani",
        "games": "3",
        "time": "106",
        "goals": "0",
        "xG": "0.015178898349404335",
        "assists": "0",
        "xA": "0",
        "shots": "1",
        "key_passes": "0",
        "yellow_cards": "1",
        "red_cards": "0",
        "position": "D S",
        "team_title": "Borussia Dortmund",
        "npg": "0",
        "npxG": "0.015178898349404335",
        "xGChain": "0.21773949265480042",
        "xGBuildup": "0.20256058871746063"
    },
    {
        "id": "14421",
        "player_name": "Samuele Inácio",
        "games": "1",
        "time": "8",
        "goals": "0",
        "xG": "0.05087319016456604",
        "assists": "0",
        "xA": "0",
        "shots": "1",
        "key_passes": "0",
        "yellow_cards": "0",
        "red_cards": "0",
        "position": "S",
        "team_title": "Borussia Dortmund",
        "npg": "0",
        "npxG": "0.05087319016456604",
        "xGChain": "0",
        "xGBuildup": "0"
    }
]