[
    {
        "id": "11861",
        "player_name": "Stefan Schimmer",
        "games": "10",
        "time": "358",
        "goals": "4",
        "xG": "3.6219489201903343",
        "assists": "1",
        "xA": "1.3891584649682045",
        "shots": "21",
        "key_passes": "8",
        "yellow_cards": "1",
        "red_cards": "0",
        "position": "F S",
        "team_title": "FC Heidenheim",
        "npg": "4",
        "npxG": "3.6219489201903343",
        "xGChain": "5.9620322324335575",
        "xGBuildup": "1.3712111450731754"
    },
    {
        "id": "5347",
        "player_name": "Jonas Föhrenbach",
        "games": "15",
        "time": "1317",
        "goals": "1",
        "xG": "0.4812412541359663",
        "assists": "1",
        "xA": "1.743933081626892",
        "shots": "4",
        "key_passes": "18",
        "yellow_cards": "1",
        "red_cards": "0",
        "position": "D M S",
        "team_title": "FC Heidenheim",
        "npg": "1",
        "npxG": "0.4812412541359663",
        "xGChain": "2.8360123923048377",
        "xGBuildup": "1.7902913903817534"
    },
    {
        "id": "11853",
        "player_name": "Patrick Mainka",
        "games": "15",
        "time": "1350",
        "goals": "1",
        "xG": "1.3598790131509304",
        "assists": "1",
        "xA": "0.8198557533323765",
        "shots": "15",
        "key_passes": "4",
        "yellow_cards": "2",
        "red_cards": "0",
        "position": "D",
        "team_title": "FC Heidenheim",
        "npg": "1",
        "npxG": "1.3598790131509304",
        "xGChain": "3.3692396311089396",
        "xGBuildup": "3.2201626440510154"
    },
    {
        "id": "11856",
        "player_name": "Marvin Pieringer",
        "games": "9",
        "time": "479",
        "goals": "1",
        "xG": "1.8150548189878464",
        "assists": "0",
        "xA": "0.7502390239387751",
        "shots": "11",
        "key_passes": "7",
        "yellow_cards": "1",
        "red_cards": "0",
        "position": "F S",
        "team_title": "FC Heidenheim",
        "npg": "1",
        "npxG": "1.8150548189878464",
        "xGChain": "2.6495973337441683",
        "xGBuildup": "0.31270824559032917"
    },
    {
        "id": "11865",
        "player_name": "Jan Schöppner",
        "games": "14",
        "time": "1049",
        "goals": "1",
        "xG": "0.4278137367218733",
        "assists": "0",
        "xA": "1.1695856004953384",
        "shots": "7",
        "key_passes": "4",
        "yellow_cards": "4",
        "red_cards": "0",
        "position": "M S",
        "team_title": "FC Heidenheim",
        "npg": "1",
        "npxG": "0.4278137367218733",
        "xGChain": "3.2151317289099097",
        "xGBuildup": "2.500277510844171"
    },
    {
        "id": "12053",
        "player_name": "Mikkel Kaufmann",
        "games": "9",
        "time": "408",
        "goals": "1",
        "xG": "0.7143451198935509",
        "assists": "1",
        "xA": "1.2234492003917694",
        "shots": "8",
        "key_passes": "3",
        "yellow_cards": "2",
        "red_cards": "0",
        "position": "F S",
        "team_title": "FC Heidenheim",
        "npg": "1",
        "npxG": "0.7143451198935509",
        "xGChain": "1.716015174984932",
        "xGBuildup": "0.10937948524951935"
    },
    {
        "id": "12986",
        "player_name": "Léo Scienza",
        "games": "2",
        "time": "180",
        "goals": "1",
        "xG": "0.1424524337053299",
        "assists": "0",
        "xA": "1.3223831057548523",
        "shots": "4",
        "key_passes": "3",
        "yellow_cards": "0",
        "red_cards": "0",
        "position": "M",
        "team_title": "FC Heidenheim",
        "npg": "1",
        "npxG": "0.1424524337053299",
        "xGChain": "1.1770203709602356",
        "xGBuildup": "0.7020066827535629"
    },
    {
        "id": "12988",
        "player_name": "Sirlord Conteh",
        "games": "5",
        "time": "251",
        "goals": "1",
        "xG": "1.7836451679468155",
        "assists": "1",
        "xA": "0.490153968334198",
        "shots": "5",
        "key_passes": "6",
        "yellow_cards": "1",
        "red_cards": "0",
        "position": "F M S",
        "team_title": "FC Heidenheim",
        "npg": "1",
        "npxG": "1.7836451679468155",
        "xGChain": "1.5357967913150787",
        "xGBuildup": "0.21061554551124573"
    },
    {
        "id": "13323",
        "player_name": "Budu Zivzivadze",
        "games": "8",
        "time": "383",
        "goals": "1",
        "xG": "2.1716021299362183",
        "assists": "0",
        "xA": "0.07982459291815758",
        "shots": "7",
        "key_passes": "2",
        "yellow_cards": "0",
        "red_cards": "1",
        "position": "F S",
        "team_title": "FC Heidenheim",
        "npg": "1",
        "npxG": "2.1716021299362183",
        "xGChain": "2.3895889297127724",
        "xGBuildup": "0.2098880633711815"
    },
    {
        "id": "13862",
        "player_name": "Adam Kölle",
        "games": "5",
        "time": "65",
        "goals": "1",
        "xG": "0.6129398345947266",
        "assists": "0",
        "xA": "0.03532744571566582",
        "shots": "2",
        "key_passes": "1",
        "yellow_cards": "1",
        "red_cards": "0",
        "position": "S",
        "team_title": "FC Heidenheim",
        "npg": "1",
        "npxG": "0.6129398345947266",
        "xGChain": "0.1584107019007206",
        "xGBuildup": "0.03532744571566582"
    },
    {
        "id": "4312",
        "player_name": "Marnon Busch",
        "games": "15",
        "time": "838",
        "goals": "0",
        "xG": "0.3565447935834527",
        "assists": "2",
        "xA": "1.276211204007268",
        "shots": "4",
        "key_passes": "6",
        "yellow_cards": "1",
        "red_cards": "0",
        "position": "D M S",
        "team_title": "FC Heidenheim",
        "npg": "0",
        "npxG": "0.3565447935834527",
        "xGChain": "2.514748863875866",
        "xGBuildup": "1.7162202559411526"
    },
    {
        "id": "6411",
        "player_name": "Niklas Dorsch",
        "games": "14",
        "time": "921",
        "goals": "0",
        "xG": "0.37505894526839256",
        "assists": "0",
        "xA": "0.5030533643439412",
        "shots": "11",
        "key_passes": "8",
        "yellow_cards": "0",
        "red_cards": "0",
        "position": "M S",
        "team_title": "FC Heidenheim",
        "npg": "0",
        "npxG": "0.37505894526839256",
        "xGChain": "2.9844972118735313",
        "xGBuildup": "2.8149833753705025"
    },
    {
        "id": "8854",
        "player_name": "Tim Siersleben",
        "games": "11",
        "time": "822",
        "goals": "0",
        "xG": "0.20233535580337048",
        "assists": "0",
        "xA": "0.11557023227214813",
        "shots": "4",
        "key_passes": "2",
        "yellow_cards": "1",
        "red_cards": "0",
        "position": "D S",
        "team_title": "FC Heidenheim",
        "npg": "0",
        "npxG": "0.20233535580337048",
        "xGChain": "1.3642809763550758",
        "xGBuildup": "1.074270966462791"
    },
    {
        "id": "9753",
        "player_name": "Diant Ramaj",
        "games": "15",
        "time": "1350",
        "goals": "0",
        "xG": "0",
        "assists": "0",
        "xA": "0",
        "shots": "0",
        "key_passes": "0",
        "yellow_cards": "1",
        "red_cards": "0",
        "position": "GK",
        "team_title": "FC Heidenheim",
        "npg": "0",
        "npxG": "0",
        "xGChain": "2.290756866335869",
        "xGBuildup": "2.290756866335869"
    },
    {
        "id": "10248",
        "player_name": "Arijon Ibrahimovic",
        "games": "15",
        "time": "1107",
        "goals": "0",
        "xG": "2.222836909815669",
        "assists": "2",
        "xA": "2.045885233208537",
        "shots": "21",
        "key_passes": "27",
        "yellow_cards": "0",
        "red_cards": "0",
        "position": "F M S",
        "team_title": "FC Heidenheim",
        "npg": "0",
        "npxG": "2.222836909815669",
        "xGChain": "4.374845132231712",
        "xGBuildup": "1.5803187927231193"
    },
    {
        "id": "11855",
        "player_name": "Adrian Beck",
        "games": "12",
        "time": "527",
        "goals": "0",
        "xG": "0.24663633480668068",
        "assists": "0",
        "xA": "0.4438072331249714",
        "shots": "5",
        "key_passes": "7",
        "yellow_cards": "0",
        "red_cards": "0",
        "position": "M S",
        "team_title": "FC Heidenheim",
        "npg": "0",
        "npxG": "0.24663633480668068",
        "xGChain": "2.548609748482704",
        "xGBuildup": "2.175685005262494"
    },
    {
        "id": "11859",
        "player_name": "Omar Traoré",
        "games": "15",
        "time": "889",
        "goals": "0",
        "xG": "0.18175849504768848",
        "assists": "2",
        "xA": "1.323072349652648",
        "shots": "7",
        "key_passes": "9",
        "yellow_cards": "2",
        "red_cards": "0",
        "position": "D S",
        "team_title": "FC Heidenheim",
        "npg": "0",
        "npxG": "0.18175849504768848",
        "xGChain": "2.506662323139608",
        "xGBuildup": "2.021746102720499"
    },
    {
        "id": "11864",
        "player_name": "Benedikt Gimber",
        "games": "10",
        "time": "612",
        "goals": "0",
        "xG": "0",
        "assists": "0",
        "xA": "0.21245378255844116",
        "shots": "0",
        "key_passes": "1",
        "yellow_cards": "3",
        "red_cards": "0",
        "position": "D S",
        "team_title": "FC Heidenheim",
        "npg": "0",
        "npxG": "0",
        "xGChain": "0.5131260603666306",
        "xGBuildup": "0.5131260603666306"
    },
    {
        "id": "11892",
        "player_name": "Leart Paqarada",
        "games": "1",
        "time": "6",
        "goals": "0",
        "xG": "0",
        "assists": "0",
        "xA": "0",
        "shots": "0",
        "key_passes": "0",
        "yellow_cards": "0",
        "red_cards": "0",
        "position": "D",
        "team_title": "FC Heidenheim",
        "npg": "0",
        "npxG": "0",
        "xGChain": "0",
        "xGBuildup": "0"
    },
    {
        "id": "11917",
        "player_name": "Mathias Honsak",
        "games": "12",
        "time": "665",
        "goals": "0",
        "xG": "1.469688642770052",
        "assists": "0",
        "xA": "0.27376034669578075",
        "shots": "20",
        "key_passes": "4",
        "yellow_cards": "0",
        "red_cards": "0",
        "position": "F M S",
        "team_title": "FC Heidenheim",
        "npg": "0",
        "npxG": "1.469688642770052",
        "xGChain": "3.0346971303224564",
        "xGBuildup": "1.4432509988546371"
    },
    {
        "id": "12023",
        "player_name": "Thomas Keller",
        "games": "4",
        "time": "193",
        "goals": "0",
        "xG": "0.05427293013781309",
        "assists": "0",
        "xA": "0",
        "shots": "2",
        "key_passes": "0",
        "yellow_cards": "1",
        "red_cards": "0",
        "position": "D S",
        "team_title": "FC Heidenheim",
        "npg": "0",
        "npxG": "0.05427293013781309",
        "xGChain": "0.12361487094312906",
        "xGBuildup": "0.11296646483242512"
    },
    {
        "id": "12987",
        "player_name": "Luca Kerber",
        "games": "9",
        "time": "377",
        "goals": "0",
        "xG": "0.20898379758000374",
        "assists": "0",
        "xA": "0.15216649509966373",
        "shots": "3",
        "key_passes": "2",
        "yellow_cards": "2",
        "red_cards": "0",
        "position": "M S",
        "team_title": "FC Heidenheim",
        "npg": "0",
        "npxG": "0.20898379758000374",
        "xGChain": "0.7591478768736124",
        "xGBuildup": "0.510344386100769"
    },
    {
        "id": "13429",
        "player_name": "Julian Niehues",
        "games": "11",
        "time": "612",
        "goals": "0",
        "xG": "0.22569632343947887",
        "assists": "0",
        "xA": "0.17055916786193848",
        "shots": "6",
        "key_passes": "2",
        "yellow_cards": "0",
        "red_cards": "0",
        "position": "M S",
        "team_title": "FC Heidenheim",
        "npg": "0",
        "npxG": "0.22569632343947887",
        "xGChain": "1.9276272766292095",
        "xGBuildup": "1.786613754928112"
    },
    {
        "id": "13863",
        "player_name": "Yannik Wagner",
        "games": "3",
        "time": "26",
        "goals": "0",
        "xG": "0.024279415607452393",
        "assists": "0",
        "xA": "0.2785300724208355",
        "shots": "1",
        "key_passes": "3",
        "yellow_cards": "0",
        "red_cards": "0",
        "position": "S",
        "team_title": "FC Heidenheim",
        "npg": "0",
        "npxG": "0.024279415607452393",
        "xGChain": "0.265305258333683",
        "xGBuildup": "0.07995288819074631"
    },
    {
        "id": "14096",
        "player_name": "Tobias Weigel",
        "games": "1",
        "time": "1",
        "goals": "0",
        "xG": "0",
        "assists": "0",
        "xA": "0",
        "shots": "0",
        "key_passes": "0",
        "yellow_cards": "0",
        "red_cards": "0",
        "position": "S",
        "team_title": "FC Heidenheim",
        "npg": "0",
        "npxG": "0",
        "xGChain": "0.03532744571566582",
        "xGBuildup": "0.03532744571566582"
    }
]